edge_playback/__init__.py
edge_playback/__main__.py
edge_tts/__init__.py
edge_tts/__main__.py
edge_tts/communicate.py
edge_tts/constants.py
edge_tts/exceptions.py
edge_tts/list_voices.py
edge_tts/submaker.py
edge_tts/util.py
edge_tts/version.py
edge_tts_ext-6.1.8.dist-info/LICENSE
edge_tts_ext-6.1.8.dist-info/METADATA
edge_tts_ext-6.1.8.dist-info/WHEEL
edge_tts_ext-6.1.8.dist-info/entry_points.txt
edge_tts_ext-6.1.8.dist-info/top_level.txt
edge_tts_ext-6.1.8.dist-info/RECORD
