Metadata-Version: 2.1
Name: edge-tts-ext
Version: 6.1.8
Summary: Microsoft Edge's TTS
Home-page: https://github.com/rany2/edge-tts
Author: rany
Author-email: ranygh@riseup.net
Project-URL: Bug Tracker, https://github.com/rany2/edge-tts/issues
Classifier: Programming Language :: Python :: 3
Classifier: License :: OSI Approved :: GNU General Public License v3 (GPLv3)
Classifier: Operating System :: OS Independent
Requires-Python: >=3.7
License-File: LICENSE
Requires-Dist: aiohttp (>=3.8.0)
Provides-Extra: dev
Requires-Dist: black ; extra == 'dev'
Requires-Dist: isort ; extra == 'dev'
Requires-Dist: mypy ; extra == 'dev'
Requires-Dist: pylint ; extra == 'dev'
